information_parity/__init__.py
information_parity/information_parity.py
information_parity-0.1.1.dist-info/licenses/LICENSE
information_parity-0.1.1.dist-info/METADATA
information_parity-0.1.1.dist-info/WHEEL
information_parity-0.1.1.dist-info/top_level.txt
information_parity-0.1.1.dist-info/RECORD
