Metadata-Version: 2.4
Name: information-parity
Version: 0.1.1
Summary: A Python package for measuring the relative multilingual performance of language models across different languages
Author-email: Information Parity Contributors <tsalex1992@gmail.com>
License-Expression: MIT
Project-URL: Homepage, https://github.com/tsalex1992/Information-Parity
Project-URL: Bug Tracker, https://github.com/tsalex1992/Information-Parity/issues
Project-URL: Documentation, https://github.com/tsalex1992/Information-Parity#readme
Project-URL: Source Code, https://github.com/tsalex1992/Information-Parity
Project-URL: Paper, https://aclanthology.org/2024.findings-emnlp.468
Keywords: nlp,language-models,multilingual,evaluation,information-theory
Classifier: Intended Audience :: Science/Research
Classifier: Programming Language :: Python :: 3
Classifier: Topic :: Scientific/Engineering :: Artificial Intelligence
Requires-Python: >=3.10
License-File: LICENSE
Requires-Dist: transformers>=4.51.2
Requires-Dist: torch>=2.0.0
Requires-Dist: numpy>=1.24.0
Requires-Dist: tqdm>=4.64.1
Provides-Extra: evaluation
Requires-Dist: datasets>=2.14.0; extra == "evaluation"
Dynamic: license-file
